compose_mode/__init__.py
compose_mode/_main.py
compose_mode/_main.py.bak
compose_mode/exceptions.py
compose_mode/generate.py
compose_mode/generate.py.bak
compose_mode/io.py
compose_mode/status.py
compose_mode/status.py.bak
compose_mode-0.6.0.data/scripts/compose-mode
compose_mode-0.6.0.dist-info/LICENSE
compose_mode-0.6.0.dist-info/METADATA
compose_mode-0.6.0.dist-info/WHEEL
compose_mode-0.6.0.dist-info/top_level.txt
compose_mode-0.6.0.dist-info/RECORD
